pyromaniac/__init__.py
pyromaniac/handler.py
pyromaniac/local_handler.py
pyromaniac/plot.py
pyromaniac/posterior.py
pyromaniac-0.5.0.dist-info/LICENSE
pyromaniac-0.5.0.dist-info/WHEEL
pyromaniac-0.5.0.dist-info/METADATA
pyromaniac-0.5.0.dist-info/RECORD
