Metadata-Version: 2.1
Name: pyromaniac
Version: 0.5.0
Summary: Helper modules for pyro.
Author: Harald Vohringer
Requires-Python: >=3.8.1,<3.11
Classifier: Programming Language :: Python :: 3
Classifier: Programming Language :: Python :: 3.10
Classifier: Programming Language :: Python :: 3.9
Requires-Dist: pyro-ppl (>=1.8.0)
